threadinglogger/__init__.py
threadinglogger-0.0.6.dist-info/METADATA
threadinglogger-0.0.6.dist-info/WHEEL
threadinglogger-0.0.6.dist-info/licenses/LICENSE
threadinglogger-0.0.6.dist-info/RECORD
