Metadata-Version: 2.1
Name: threadinglogger
Version: 0.0.6
Summary: Logger using a thread.
Project-URL: Homepage, https://github.com/chorong8883/threadinglogger
Author-email: Chor <chorong8883@gmail.com>
License-File: LICENSE
Classifier: License :: OSI Approved :: MIT License
Classifier: Operating System :: POSIX :: Linux
Classifier: Programming Language :: Python :: 3.9
Requires-Python: >=3.9
